Workbook

Sheet Dashboard
A1: TABLEAU DE BORD - REVENUE MANAGEMENT
A3: Hôtel: | B3: HOTEL PRESTIGE BUSINESS - DAKAR | F3: INDICATEURS CLÉS - MAI 2026
A4: Capacité totale: | B4: 180 | D4: chambres
F5: RevPAR | G5: ='Données & Forecast'!K5 -> 193.07129
A6: Type de chambre | B6: Nombre | C6: Surface (m²) | D6: Prix de base | F6: ADR | G6: ='Données & Forecast'!L5 -> 249.00524
A7: Supérieure | B7: 80 | C7: 28 | D7: 180 | F7: Taux d'occupation | G7: ='Données & Forecast'!M5 -> 0.77537037
A8: Deluxe Vue Mer | B8: 60 | C8: 35 | D8: 260 | F8: TRevPAR | G8: ='Données & Forecast'!N5 -> 245.20053
A9: Executive | B9: 30 | C9: 42 | D9: 340
A10: Junior Suite | B10: 10 | C10: 55 | D10: 450
A12: PERFORMANCE PAR SEGMENT CLIENT
A13: Segment | B13: % Réservations | C13: ADR Moyen | D13: Contribution CA
A14: Corporate Contractuel | B14: ='Analyse Segmentation'!C4 -> 0.31067961 | C14: ='Analyse Segmentation'!D4 -> 215 | D14: ='Analyse Segmentation'!E4 -> 275200
A15: Corporate Spot | B15: ='Analyse Segmentation'!C5 -> 0.23058252 | C15: ='Analyse Segmentation'!D5 -> 275 | D15: ='Analyse Segmentation'!E5 -> 261250
A16: Transient (Individuel) | B16: ='Analyse Segmentation'!C6 -> 0.18932039 | C16: ='Analyse Segmentation'!D6 -> 240 | D16: ='Analyse Segmentation'!E6 -> 187200
A17: Loisirs | B17: ='Analyse Segmentation'!C7 -> 0.15048544 | C17: ='Analyse Segmentation'!D7 -> 235 | D17: ='Analyse Segmentation'!E7 -> 145700
A18: Groupes/Événements | B18: ='Analyse Segmentation'!C8 -> 0.11893204 | C18: ='Analyse Segmentation'!D8 -> 205 | D18: ='Analyse Segmentation'!E8 -> 100450

Sheet Guide KPI & Méthodologie
A1: GUIDE DES KPI & MÉTHODOLOGIE REVENUE MANAGEMENT
A3: 1. INDICATEURS CLÉS DE PERFORMANCE (KPI)
A4: KPI | B4: Formule | C4: Définition | D4: Benchmark Dakar 4-5★
A5: RevPAR | B5: Revenus chambres / Chambres disponibles | C5: Revenue Per Available Room - Mesure la performance globale (prix × occupation) | D5: 150-220€
A6: ADR | B6: Revenus chambres / Chambres vendues | C6: Average Daily Rate - Tarif moyen réellement pratiqué | D6: 200-300€
A7: Taux occupation | B7: Chambres vendues / Chambres disponibles | C7: % de remplissage de l'hôtel | D7: 70-85%
A8: TRevPAR | B8: (Revenus chambres + Autres CA) / Ch. dispo | C8: Total Revenue PAR - Inclut F&B, spa, services | D8: 190-280€
A9: Yield Index | B9: RevPAR réalisé / RevPAR potentiel max | C9: Indice d'optimisation du pricing (non calculé ici) | D9: >85%
A11: 2. SEGMENTATION CLIENT
A12: Segment | B12: Définition | C12: Caractéristiques | D12: Stratégie Pricing
A13: Corporate Contractuel | B13: Entreprises avec contrat annuel négocié | C13: Volume stable, tarifs fixes, faible élasticité prix | D13: Remise 10-20%, garantie de disponibilité
A14: Corporate Spot | B14: Voyageurs d'affaires sans contrat (ad-hoc) | C14: Réservation courte (J-3), forte demande semaine, prix moins sensible | D14: Prix premium, restrictions LOS minimales
A15: Transient | B15: Clients individuels (OTA, direct, walk-in) | C15: Mix affaires/loisirs, forte élasticité prix, canaux variés | D15: Pricing dynamique pur, fence tarifaires
A16: Loisirs | B16: Touristes, couples, familles | C16: Séjour week-end/vacances, sensible au prix, packages | D16: Promotions WE, bundles (spa, F&B)
A17: Groupes/Événements | B17: Séminaires, conférences, mariages | C17: Volume important, négociation, LOS long | D17: Remise volume, minimums garantis
A19: 3. TYPES DE CHAMBRES - INSPIRÉ RADISSON BLU & KING FAHD PALACE DAKAR
A20: Type | B20: Surface | C20: Équipements clés | D20: Segment cible principal
A21: Supérieure | B21: 28m² | C21: Vue ville/jardin, lit king, bureau, wifi | D21: Corporate contractuel, Transient
A22: Deluxe Vue Mer | B22: 35m² | C22: Vue océan, balcon, baignoire, Nespresso | D22: Corporate spot, Loisirs haut de gamme
A23: Executive | B23: 42m² | C23: Salon séparé, espace travail, accès lounge | D23: Corporate spot, VIP
A24: Junior Suite | B24: 55m² | C24: Chambre + salon, 2 TV, bar, terrasse | D24: Loisirs luxe, Groupes VIP
A26: 4. LOGIQUE PRICING DYNAMIQUE
A27: • DEMANDE >90% → Prix +35% (Stratégie Premium) - Événements majeurs, haute saison
A28: • DEMANDE 75-90% → Prix +15% (Optimisation) - Forte demande semaine
A29: • DEMANDE 60-75% → Prix de base (Standard) - Demande normale
A30: • DEMANDE 45-60% → Prix -10% (Stimulation) - Début week-end, basse saison
A31: • DEMANDE <45% → Prix -20% (Promotion) - Week-ends creux, packages nécessaires
A33: 5. NOTES MÉTHODOLOGIQUES
A34: → Les prix de base sont inspirés du marché hôtelier 4-5★ Dakar (Radisson Blu, King Fahd Palace)
A35: → La saisonnalité reflète le climat sénégalais : Haute saison Nov-Mai, Basse saison Juin-Oct
A36: → Les événements intègrent le calendrier CEDEAO, conférences internationales, salons
A37: → Le mix segments est typique d'un hôtel urbain d'affaires Dakar (60% corporate, 40% loisirs)
A38: → Les autres revenus (F&B, spa) représentent 25-30% du CA chambres pour ce positionnement
A39: → Ce modèle peut être adapté à tout hôtel 3-5★ en modifiant les cellules BLEUES (inputs)

Sheet Calendrier Pricing
A1: CALENDRIER PRICING DYNAMIQUE - MAI 2026
A3: Date | B3: Jour | C3: Saison | D3: Événement | E3: Supérieure | F3: Deluxe | G3: Executive | H3: Junior Suite | I3: Occup. Prév. | J3: Demande | K3: Stratégie
A4: 01/05/2026 | B4: Ven | C4: Haute | E4: 180 | F4: 260 | G4: 340 | H4: 450 | I4: 0.68 | J4: 62 | K4: Standard
A5: 02/05/2026 | B5: Sam | C5: Haute | E5: 144 | F5: 208 | G5: 272 | H5: 360 | I5: 0.42 | J5: 38 | K5: Promotion WE
A6: 03/05/2026 | B6: Dim | C6: Haute | E6: 144 | F6: 208 | G6: 272 | H6: 360 | I6: 0.42 | J6: 38 | K6: Promotion WE
A7: 04/05/2026 | B7: Lun | C7: Haute | E7: 180 | F7: 260 | G7: 340 | H7: 450 | I7: 0.76 | J7: 72 | K7: Standard
A8: 05/05/2026 | B8: Mar | C8: Haute | E8: 180 | F8: 260 | G8: 340 | H8: 450 | I8: 0.76 | J8: 72 | K8: Standard
A9: 06/05/2026 | B9: Mer | C9: Haute | E9: 180 | F9: 260 | G9: 340 | H9: 450 | I9: 0.76 | J9: 72 | K9: Standard
A10: 07/05/2026 | B10: Jeu | C10: Haute | E10: 180 | F10: 260 | G10: 340 | H10: 450 | I10: 0.76 | J10: 72 | K10: Standard
A11: 08/05/2026 | B11: Ven | C11: Haute | E11: 180 | F11: 260 | G11: 340 | H11: 450 | I11: 0.68 | J11: 62 | K11: Standard
A12: 09/05/2026 | B12: Sam | C12: Haute | E12: 144 | F12: 208 | G12: 272 | H12: 360 | I12: 0.42 | J12: 38 | K12: Promotion WE
A13: 10/05/2026 | B13: Dim | C13: Haute | E13: 144 | F13: 208 | G13: 272 | H13: 360 | I13: 0.42 | J13: 38 | K13: Promotion WE
A14: 11/05/2026 | B14: Lun | C14: Haute | E14: 180 | F14: 260 | G14: 340 | H14: 450 | I14: 0.76 | J14: 72 | K14: Standard
A15: 12/05/2026 | B15: Mar | C15: Haute | E15: 180 | F15: 260 | G15: 340 | H15: 450 | I15: 0.76 | J15: 72 | K15: Standard
A16: 13/05/2026 | B16: Mer | C16: Haute | E16: 180 | F16: 260 | G16: 340 | H16: 450 | I16: 0.76 | J16: 72 | K16: Standard
A17: 14/05/2026 | B17: Jeu | C17: Haute | D17: Sommet CEDEAO | E17: 243 | F17: 351 | G17: 459 | H17: 607 | I17: 0.93 | J17: 96 | K17: Premium
A18: 15/05/2026 | B18: Ven | C18: Haute | D18: Sommet CEDEAO | E18: 243 | F18: 351 | G18: 459 | H18: 607 | I18: 0.93 | J18: 96 | K18: Premium
A19: 16/05/2026 | B19: Sam | C19: Haute | D19: Sommet CEDEAO | E19: 243 | F19: 351 | G19: 459 | H19: 607 | I19: 0.93 | J19: 96 | K19: Premium
A20: 17/05/2026 | B20: Dim | C20: Haute | E20: 144 | F20: 208 | G20: 272 | H20: 360 | I20: 0.42 | J20: 38 | K20: Promotion WE
A21: 18/05/2026 | B21: Lun | C21: Haute | E21: 180 | F21: 260 | G21: 340 | H21: 450 | I21: 0.76 | J21: 72 | K21: Standard
A22: 19/05/2026 | B22: Mar | C22: Haute | E22: 180 | F22: 260 | G22: 340 | H22: 450 | I22: 0.76 | J22: 72 | K22: Standard
A23: 20/05/2026 | B23: Mer | C23: Haute | E23: 180 | F23: 260 | G23: 340 | H23: 450 | I23: 0.76 | J23: 72 | K23: Standard
A24: 21/05/2026 | B24: Jeu | C24: Haute | E24: 180 | F24: 260 | G24: 340 | H24: 450 | I24: 0.76 | J24: 72 | K24: Standard
A25: 22/05/2026 | B25: Ven | C25: Haute | D25: Africa Tech Summit | E25: 243 | F25: 351 | G25: 459 | H25: 607 | I25: 0.93 | J25: 96 | K25: Premium
A26: 23/05/2026 | B26: Sam | C26: Haute | D26: Africa Tech Summit | E26: 243 | F26: 351 | G26: 459 | H26: 607 | I26: 0.93 | J26: 96 | K26: Premium
A27: 24/05/2026 | B27: Dim | C27: Haute | E27: 144 | F27: 208 | G27: 272 | H27: 360 | I27: 0.42 | J27: 38 | K27: Promotion WE
A28: 25/05/2026 | B28: Lun | C28: Haute | E28: 180 | F28: 260 | G28: 340 | H28: 450 | I28: 0.76 | J28: 72 | K28: Standard
A29: 26/05/2026 | B29: Mar | C29: Haute | E29: 180 | F29: 260 | G29: 340 | H29: 450 | I29: 0.76 | J29: 72 | K29: Standard
A30: 27/05/2026 | B30: Mer | C30: Haute | E30: 180 | F30: 260 | G30: 340 | H30: 450 | I30: 0.76 | J30: 72 | K30: Standard
A31: 28/05/2026 | B31: Jeu | C31: Haute | E31: 180 | F31: 260 | G31: 340 | H31: 450 | I31: 0.76 | J31: 72 | K31: Standard
A32: 29/05/2026 | B32: Ven | C32: Haute | E32: 180 | F32: 260 | G32: 340 | H32: 450 | I32: 0.68 | J32: 62 | K32: Standard
A33: 30/05/2026 | B33: Sam | C33: Haute | E33: 144 | F33: 208 | G33: 272 | H33: 360 | I33: 0.42 | J33: 38 | K33: Promotion WE
A34: 31/05/2026 | B34: Dim | C34: Haute | E34: 144 | F34: 208 | G34: 272 | H34: 360 | I34: 0.42 | J34: 38 | K34: Promotion WE

Sheet Moteur de Calcul
A1: MOTEUR DE PRICING DYNAMIQUE
A3: PRIX DE BASE (EUR)
A4: Type chambre | B4: Surface | C4: Prix plancher | D4: Prix de base | E4: Prix plafond
A5: Supérieure | B5: 28m² | C5: 130 | D5: 180 | E5: 270
A6: Deluxe Vue Mer | B6: 35m² | C6: 190 | D6: 260 | E6: 380
A7: Executive | B7: 42m² | C7: 250 | D7: 340 | E7: 500
A8: Junior Suite | B8: 55m² | C8: 330 | D8: 450 | E8: 650
A11: RÈGLES DE PRICING DYNAMIQUE
A12: Niveau demande | B12: Seuil (%) | C12: Multiplicateur | D12: Stratégie | E12: Restrictions
A13: Très forte | B13: >90% | C13: 1.35 | D13: Premium | E13: Min 2 nuits, CTA possible
A14: Forte | B14: 75-90% | C14: 1.15 | D14: Optimisation | E14: Min 1 nuit
A15: Moyenne | B15: 60-75% | C15: 1 | D15: Standard | E15: Aucune
A16: Faible | B16: 45-60% | C16: 0.9 | D16: Stimulation | E16: Packages recommandés
A17: Très faible | B17: <45% | C17: 0.8 | D17: Promotion | E17: Offres WE, bundles F&B
A20: SEGMENTS CLIENTS & REMISES
A21: Segment | B21: Remise max | C21: Commission | D21: LOS minimum
A22: Corporate Contractuel | B22: 0.18 | C22: 0.05 | D22: 1
A23: Corporate Spot | B23: 0.1 | C23: 0.1 | D23: 1
A24: Transient (Individuel) | B24: 0.05 | C24: 0.15 | D24: 1
A25: Loisirs | B25: 0.08 | C25: 0.18 | D25: 2
A26: Groupes/Événements | B26: 0.22 | C26: 0.08 | D26: 3

Sheet Données & Forecast
A1: DONNÉES HISTORIQUES & PRÉVISIONS
A3: Mois | B3: Année | C3: Saison | D3: Ch. Vendues | E3: Ch. Dispo | F3: Occupation | G3: ADR Moyen | H3: Revenus Ch. | I3: Autres Rev. | J3: TRevPAR | K3: RevPAR | L3: ADR | M3: Taux Occ | N3: TRevPAR Final
A4: Juin | B4: 2025 | C4: Moyenne | D4: 3810 | E4: 5400 | F4: 0.70573045 | G4: 232.61803 | H4: 886274.7 | I4: 239294.17 | J4: 208.43868 | K4: =H4/E4 -> 164.12495 | L4: =H4/D4 -> 232.61803 | M4: =D4/E4 -> 0.70555556 | N4: =(H4+I4)/E4 -> 208.43868
A5: Juil | B5: 2025 | C5: Haute | D5: 4187 | E5: 5400 | F5: 0.77544429 | G5: 249.00524 | H5: 1042584.9 | I5: 281497.94 | J5: 245.20053 | K5: =H5/E5 -> 193.07129 | L5: =H5/D5 -> 249.00524 | M5: =D5/E5 -> 0.77537037 | N5: =(H5+I5)/E5 -> 245.20053
A6: Août | B6: 2025 | C6: Haute | D6: 4406 | E6: 5400 | F6: 0.81610184 | G6: 265.43909 | H6: 1169524.6 | I6: 315771.65 | J6: 275.05486 | K6: =H6/E6 -> 216.57863 | L6: =H6/D6 -> 265.43909 | M6: =D6/E6 -> 0.81592593 | N6: =(H6+I6)/E6 -> 275.05486
A7: Sept | B7: 2025 | C7: Moyenne | D7: 3720 | E7: 5400 | F7: 0.68892713 | G7: 225.8097 | H7: 840012.09 | I7: 226803.26 | J7: 197.5584 | K7: =H7/E7 -> 155.55779 | L7: =H7/D7 -> 225.8097 | M7: =D7/E7 -> 0.68888889 | N7: =(H7+I7)/E7 -> 197.5584
A8: Oct | B8: 2025 | C8: Moyenne | D8: 3958 | E8: 5400 | F8: 0.7329719 | G8: 228.03139 | H8: 902548.23 | I8: 243688.02 | J8: 212.26597 | K8: =H8/E8 -> 167.13856 | L8: =H8/D8 -> 228.03139 | M8: =D8/E8 -> 0.73296296 | N8: =(H8+I8)/E8 -> 212.26597
A9: Nov | B9: 2025 | C9: Basse | D9: 3130 | E9: 5400 | F9: 0.57968778 | G9: 188.51254 | H9: 590044.25 | I9: 159311.95 | J9: 138.76967 | K9: =H9/E9 -> 109.26745 | L9: =H9/D9 -> 188.51254 | M9: =D9/E9 -> 0.57962963 | N9: =(H9+I9)/E9 -> 138.76967
A10: Déc | B10: 2025 | C10: Basse | D10: 2863 | E10: 5400 | F10: 0.53022874 | G10: 182.89656 | H10: 523632.86 | I10: 141380.87 | J10: 123.15069 | K10: =H10/E10 -> 96.969049 | L10: =H10/D10 -> 182.89656 | M10: =D10/E10 -> 0.53018519 | N10: =(H10+I10)/E10 -> 123.15069
A11: Jan | B11: 2026 | C11: Basse | D11: 2830 | E11: 5400 | F11: 0.52414689 | G11: 182.34748 | H11: 516043.37 | I11: 139331.71 | J11: 121.36575 | K11: =H11/E11 -> 95.563586 | L11: =H11/D11 -> 182.34748 | M11: =D11/E11 -> 0.52407407 | N11: =(H11+I11)/E11 -> 121.36575
A12: Fév | B12: 2026 | C12: Moyenne | D12: 3950 | E12: 5400 | F12: 0.73163044 | G12: 215.90645 | H12: 852830.46 | I12: 230264.23 | J12: 200.57309 | K12: =H12/E12 -> 157.93157 | L12: =H12/D12 -> 215.90645 | M12: =D12/E12 -> 0.73148148 | N12: =(H12+I12)/E12 -> 200.57309
A13: Mars | B13: 2026 | C13: Moyenne | D13: 3878 | E13: 5400 | F13: 0.71832865 | G13: 232.58881 | H13: 901979.39 | I13: 243534.44 | J13: 212.13219 | K13: =H13/E13 -> 167.03322 | L13: =H13/D13 -> 232.58881 | M13: =D13/E13 -> 0.71814815 | N13: =(H13+I13)/E13 -> 212.13219
A14: Avril | B14: 2026 | C14: Haute | D14: 4176 | E14: 5400 | F14: 0.77343379 | G14: 247.73833 | H14: 1034555.3 | I14: 279329.92 | J14: 243.31207 | K14: =H14/E14 -> 191.58431 | L14: =H14/D14 -> 247.73833 | M14: =D14/E14 -> 0.77333333 | N14: =(H14+I14)/E14 -> 243.31207
A15: Mai | B15: 2026 | C15: Haute | D15: 4202 | E15: 5400 | F15: 0.77815511 | G15: 262.30075 | H15: 1102187.7 | I15: 297590.69 | J15: 259.21823 | K15: =H15/E15 -> 204.10884 | L15: =H15/D15 -> 262.30075 | M15: =D15/E15 -> 0.77814815 | N15: =(H15+I15)/E15 -> 259.21823

Sheet Analyse Segmentation
A1: ANALYSE PAR SEGMENT CLIENT
A3: Segment | B3: Nuitées | C3: % Mix | D3: ADR Moyen | E3: CA Total
A4: Corporate Contractuel | B4: 1280 | C4: =B4/4120 -> 0.31067961 | D4: 215 | E4: =B4*D4 -> 275200
A5: Corporate Spot | B5: 950 | C5: =B5/4120 -> 0.23058252 | D5: 275 | E5: =B5*D5 -> 261250
A6: Transient (Individuel) | B6: 780 | C6: =B6/4120 -> 0.18932039 | D6: 240 | E6: =B6*D6 -> 187200
A7: Loisirs | B7: 620 | C7: =B7/4120 -> 0.15048544 | D7: 235 | E7: =B7*D7 -> 145700
A8: Groupes/Événements | B8: 490 | C8: =B8/4120 -> 0.11893204 | D8: 205 | E8: =B8*D8 -> 100450
A9: TOTAL | B9: =SUM(B4:B8) -> 4120 | C9: 100% | E9: =SUM(E4:E8) -> 969800

Sheet Scénarios & Simulations
A1: SIMULATIONS PRICING - WHAT-IF ANALYSIS
A3: SCÉNARIO 1: Impact variation prix (-10% / +10%)
A4: Paramètre | B4: Actuel | C4: Prix -10% | D4: Prix +10%
A5: ADR Deluxe | B5: 260 | C5: =B5*0.9 -> 234 | D5: =B5*1.1 -> 286
A6: Occupation estimée | B6: 0.76 | C6: 0.84 | D6: 0.7
A7: RevPAR | B7: =B5*B6 -> 197.6 | C7: =C5*C6 -> 196.56 | D7: =D5*D6 -> 200.2
A8: Revenus mensuels | B8: =B7*5400 -> 1067040 | C8: =C7*5400 -> 1061424 | D8: =D7*5400 -> 1081080
